LICENSE.txt
MANIFEST.in
README.md
setup.py
src/docker_remote/__init__.py
src/docker_remote/__main__.py
src/docker_remote/config.py
src/docker_remote.egg-info/PKG-INFO
src/docker_remote.egg-info/SOURCES.txt
src/docker_remote.egg-info/dependency_links.txt
src/docker_remote.egg-info/entry_points.txt
src/docker_remote.egg-info/requires.txt
src/docker_remote.egg-info/top_level.txt
src/docker_remote/client/__init__.py
src/docker_remote/client/log.py
src/docker_remote/core/__init__.py
src/docker_remote/core/remotepy.py
src/docker_remote/core/subp.py
src/docker_remote/core/tunnel.py
src/docker_remote/host/__init__.py
src/docker_remote/host/dockerhost.py
src/docker_remote/host/projects.py