Metadata-Version: 1.0
Name: docker-remote
Version: 1.1.0
Summary: Docker-remote is a wrapper for docker-compose to manage compositions on a remote machine easily.
Home-page: https://github.com/NiklasRosenstein/docker-remote
Author: Niklas Rosenstein
Author-email: rosensteinniklas@gmail.com
License: MIT
Platform: UNKNOWN
